{
  "ProfilePage": "ProfilePage",
  "decrement": "decrement",
  "increment": "increment",
  "toggle": "toggle",
  "toogle": "toogle",
  "Войти": "Войти",
  "Выйти": "Выйти",
  "Главная": "Главная",
  "Главная страница": "Главная страница",
  "Имя пользователя": "Имя пользователя",
  "Кинуть ошибку": "Кинуть ошибку",
  "Короткий язык": "Короткий язык",
  "Логин": "Логин",
  "Неверное имя пользователя или пароль": "Неверное имя пользователя или пароль",
  "О нас": "О нас",
  "О сайте": "О сайте",
  "Обновить страницу": "Обновить страницу",
  "Пароль": "Пароль",
  "Произошла непредвиденная ошибка": "Произошла непредвиденная ошибка",
  "Свернуть": "Свернуть",
  "Страница не найдена": "Страница не найдена",
  "Форма авторизации": "Форма авторизации",
  "Язык": "Язык"
}
